rholambda/__init__.py
rholambda/client.py
rholambda-0.0.1.dist-info/LICENSE
rholambda-0.0.1.dist-info/METADATA
rholambda-0.0.1.dist-info/WHEEL
rholambda-0.0.1.dist-info/top_level.txt
rholambda-0.0.1.dist-info/RECORD
