Metadata-Version: 2.1
Name: rholambda
Version: 0.0.1
Summary: Python client for the Rholambda API
Home-page: 
Author: Ajith
Author-email: ajithovijaya@gmail.com
Classifier: Programming Language :: Python :: 3
Classifier: License :: OSI Approved :: MIT License
Classifier: Operating System :: OS Independent
Requires-Python: >=3.6
License-File: LICENSE
Requires-Dist: requests >=2.25.0
